{"statuses":[{"created_at":"Sat Apr 02 12:13:48 +0000 2016","id":716237192750882820,"id_str":"716237192750882820","text":"RT @ChelseaFC: That's Loftus-Cheek's first Premier League goal and it's well deserved after a bright start. #CFCLive","entities":{"hashtags":[{"text":"CFCLive","indices":[108,116]}],"symbols":[],"user_mentions":[{"screen_name":"ChelseaFC","name":"Chelsea FC","id":22910295,"id_str":"22910295","indices":[3,13]}],"urls":[]},"truncated":false,"metadata":{"iso_language_code":"en","result_type":"recent"},"source":"\u003ca href=\"http:\/\/twitter.com\/download\/iphone\" rel=\"nofollow\"\u003eTwitter for iPhone\u003c\/a\u003e","in_reply_to_status_id":null,"in_reply_to_status_id_str":null,"in_reply_to_user_id":null,"in_reply_to_user_id_str":null,"in_reply_to_screen_name":null,"user":{"id":162798307,"id_str":"162798307","name":"Jordan Parchment","screen_name":"JordanParchmnt","location":"","description":"FRTV Student at CCCU","url":null,"entities":{"description":{"urls":[]}},"protected":false,"followers_count":127,"friends_count":109,"listed_count":1,"created_at":"Sun Jul 04 18:21:36 +0000 2010","favourites_count":1058,"utc_offset":3600,"time_zone":"London","geo_enabled":false,"verified":false,"statuses_count":4810,"lang":"en","contributors_enabled":false,"is_translator":false,"is_translation_enabled":false,"profile_background_color":"C0DEED","profile_background_image_url":"http:\/\/abs.twimg.com\/images\/themes\/theme1\/bg.png","profile_background_image_url_https":"https:\/\/abs.twimg.com\/images\/themes\/theme1\/bg.png","profile_background_tile":false,"profile_image_url":"http:\/\/pbs.twimg.com\/profile_images\/596814637485727744\/FPkegXLd_normal.jpg","profile_image_url_https":"https:\/\/pbs.twimg.com\/profile_images\/596814637485727744\/FPkegXLd_normal.jpg","profile_banner_url":"https:\/\/pbs.twimg.com\/profile_banners\/162798307\/1438199104","profile_link_color":"001EB3","profile_sidebar_border_color":"C0DEED","profile_sidebar_fill_color":"DDEEF6","profile_text_color":"333333","profile_use_background_image":true,"has_extended_profile":false,"default_profile":false,"default_profile_image":false,"following":false,"follow_request_sent":false,"notifications":false},"geo":null,"coordinates":null,"place":null,"contributors":null,"retweeted_status":{"created_at":"Sat Apr 02 12:12:54 +0000 2016","id":716236967646732288,"id_str":"716236967646732288","text":"That's Loftus-Cheek's first Premier League goal and it's well deserved after a bright start. #CFCLive","entities":{"hashtags":[{"text":"CFCLive","indices":[93,101]}],"symbols":[],"user_mentions":[],"urls":[]},"truncated":false,"metadata":{"iso_language_code":"en","result_type":"recent"},"source":"\u003ca href=\"http:\/\/twitter.com\" rel=\"nofollow\"\u003eTwitter Web Client\u003c\/a\u003e","in_reply_to_status_id":null,"in_reply_to_status_id_str":null,"in_reply_to_user_id":null,"in_reply_to_user_id_str":null,"in_reply_to_screen_name":null,"user":{"id":22910295,"id_str":"22910295","name":"Chelsea FC","screen_name":"ChelseaFC","location":"London, England","description":"The official Twitter account of Premier League champions Chelsea FC. For enquiries visit: https:\/\/t.co\/6AE0WNqdOH","url":"https:\/\/t.co\/7dGFqETrL0","entities":{"url":{"urls":[{"url":"https:\/\/t.co\/7dGFqETrL0","expanded_url":"http:\/\/www.chelseafc.com","display_url":"chelseafc.com","indices":[0,23]}]},"description":{"urls":[{"url":"https:\/\/t.co\/6AE0WNqdOH","expanded_url":"http:\/\/che.lc\/iBt6ES","display_url":"che.lc\/iBt6ES","indices":[90,113]}]}},"protected":false,"followers_count":6745468,"friends_count":229,"listed_count":19627,"created_at":"Thu Mar 05 11:54:25 +0000 2009","favourites_count":10017,"utc_offset":3600,"time_zone":"London","geo_enabled":true,"verified":true,"statuses_count":57848,"lang":"en","contributors_enabled":false,"is_translator":false,"is_translation_enabled":true,"profile_background_color":"023F84","profile_background_image_url":"http:\/\/pbs.twimg.com\/profile_background_images\/636517723892252672\/DUnOnH-G.jpg","profile_background_image_url_https":"https:\/\/pbs.twimg.com\/profile_background_images\/636517723892252672\/DUnOnH-G.jpg","profile_background_tile":false,"profile_image_url":"http:\/\/pbs.twimg.com\/profile_images\/668322198537531392\/9BcEHF15_normal.jpg","profile_image_url_https":"https:\/\/pbs.twimg.com\/profile_images\/668322198537531392\/9BcEHF15_normal.jpg","profile_banner_url":"https:\/\/pbs.twimg.com\/profile_banners\/22910295\/1457103014","profile_link_color":"375EF1","profile_sidebar_border_color":"FFFFFF","profile_sidebar_fill_color":"37D3FA","profile_text_color":"000000","profile_use_background_image":true,"has_extended_profile":false,"default_profile":false,"default_profile_image":false,"following":false,"follow_request_sent":false,"notifications":false},"geo":null,"coordinates":null,"place":null,"contributors":null,"is_quote_status":false,"retweet_count":487,"favorite_count":495,"favorited":false,"retweeted":false,"lang":"en"},"is_quote_status":false,"retweet_count":487,"favorite_count":0,"favorited":false,"retweeted":false,"lang":"en"},{"created_at":"Sat Apr 02 12:13:48 +0000 2016","id":716237191966560257,"id_str":"716237191966560257","text":"Goal \u26bd! Loftus-Cheek scores. Chelsea 1:0 Aston Villa. #AVLCHE via @Fanssify - https:\/\/t.co\/lwKpEpPr2s","entities":{"hashtags":[{"text":"AVLCHE","indices":[54,61]}],"symbols":[],"user_mentions":[{"screen_name":"Fanssify","name":"Fanssify","id":2291374219,"id_str":"2291374219","indices":[66,75]}],"urls":[{"url":"https:\/\/t.co\/lwKpEpPr2s","expanded_url":"http:\/\/goo.gl\/OCKAnu","display_url":"goo.gl\/OCKAnu","indices":[78,101]}]},"truncated":false,"metadata":{"iso_language_code":"et","result_type":"recent"},"source":"\u003ca href=\"http:\/\/www.fanssify.com\" rel=\"nofollow\"\u003eFanssifyApp\u003c\/a\u003e","in_reply_to_status_id":null,"in_reply_to_status_id_str":null,"in_reply_to_user_id":null,"in_reply_to_user_id_str":null,"in_reply_to_screen_name":null,"user":{"id":179505962,"id_str":"179505962","name":"Specter ","screen_name":"pddneil","location":"","description":"A little bit of this and that... @Chelseafc @fanssify","url":"https:\/\/t.co\/EMHz8RGaX5","entities":{"url":{"urls":[{"url":"https:\/\/t.co\/EMHz8RGaX5","expanded_url":"http:\/\/goo.gl\/OCKAnu","display_url":"goo.gl\/OCKAnu","indices":[0,23]}]},"description":{"urls":[]}},"protected":false,"followers_count":166,"friends_count":104,"listed_count":1,"created_at":"Tue Aug 17 13:14:19 +0000 2010","favourites_count":5,"utc_offset":null,"time_zone":null,"geo_enabled":false,"verified":false,"statuses_count":184,"lang":"en","contributors_enabled":false,"is_translator":false,"is_translation_enabled":false,"profile_background_color":"C0DEED","profile_background_image_url":"http:\/\/abs.twimg.com\/images\/themes\/theme1\/bg.png","profile_background_image_url_https":"https:\/\/abs.twimg.com\/images\/themes\/theme1\/bg.png","profile_background_tile":false,"profile_image_url":"http:\/\/pbs.twimg.com\/profile_images\/714911352943419394\/K-3zS-px_normal.jpg","profile_image_url_https":"https:\/\/pbs.twimg.com\/profile_images\/714911352943419394\/K-3zS-px_normal.jpg","profile_banner_url":"https:\/\/pbs.twimg.com\/profile_banners\/179505962\/1390089776","profile_link_color":"0084B4","profile_sidebar_border_color":"C0DEED","profile_sidebar_fill_color":"DDEEF6","profile_text_color":"333333","profile_use_background_image":true,"has_extended_profile":false,"default_profile":true,"default_profile_image":false,"following":false,"follow_request_sent":false,"notifications":false},"geo":null,"coordinates":null,"place":null,"contributors":null,"is_quote_status":false,"retweet_count":0,"favorite_count":0,"favorited":false,"retweeted":false,"possibly_sensitive":false,"lang":"et"},{"created_at":"Sat Apr 02 12:13:48 +0000 2016","id":716237191526092801,"id_str":"716237191526092801","text":"RT @ChelseaFC: GOAL!!! 1-0, Loftus-Cheek!!! #CFCLive","entities":{"hashtags":[{"text":"CFCLive","indices":[44,52]}],"symbols":[],"user_mentions":[{"screen_name":"ChelseaFC","name":"Chelsea FC","id":22910295,"id_str":"22910295","indices":[3,13]}],"urls":[]},"truncated":false,"metadata":{"iso_language_code":"nl","result_type":"recent"},"source":"\u003ca href=\"http:\/\/blackberry.com\/twitter\" rel=\"nofollow\"\u003eTwitter for BlackBerry\u00ae\u003c\/a\u003e","in_reply_to_status_id":null,"in_reply_to_status_id_str":null,"in_reply_to_user_id":null,"in_reply_to_user_id_str":null,"in_reply_to_screen_name":null,"user":{"id":2870865062,"id_str":"2870865062","name":"Agung Sullivan","screen_name":"setiawanp98","location":"Plamongan indah. Semarang City","description":"KeepTheBlueFlagFlyingHigh| ChelseaTillIDie|Sevenfoldism foREVer\u263a","url":null,"entities":{"description":{"urls":[]}},"protected":false,"followers_count":30,"friends_count":177,"listed_count":0,"created_at":"Wed Oct 22 12:20:22 +0000 2014","favourites_count":1,"utc_offset":null,"time_zone":null,"geo_enabled":false,"verified":false,"statuses_count":1260,"lang":"en","contributors_enabled":false,"is_translator":false,"is_translation_enabled":false,"profile_background_color":"C0DEED","profile_background_image_url":"http:\/\/abs.twimg.com\/images\/themes\/theme1\/bg.png","profile_background_image_url_https":"https:\/\/abs.twimg.com\/images\/themes\/theme1\/bg.png","profile_background_tile":false,"profile_image_url":"http:\/\/pbs.twimg.com\/profile_images\/697394457856106496\/YjO5PGnO_normal.jpg","profile_image_url_https":"https:\/\/pbs.twimg.com\/profile_images\/697394457856106496\/YjO5PGnO_normal.jpg","profile_banner_url":"https:\/\/pbs.twimg.com\/profile_banners\/2870865062\/1455106752","profile_link_color":"0084B4","profile_sidebar_border_color":"C0DEED","profile_sidebar_fill_color":"DDEEF6","profile_text_color":"333333","profile_use_background_image":true,"has_extended_profile":false,"default_profile":true,"default_profile_image":false,"following":false,"follow_request_sent":false,"notifications":false},"geo":null,"coordinates":null,"place":null,"contributors":null,"retweeted_status":{"created_at":"Sat Apr 02 12:10:53 +0000 2016","id":716236460341534720,"id_str":"716236460341534720","text":"GOAL!!! 1-0, Loftus-Cheek!!! #CFCLive","entities":{"hashtags":[{"text":"CFCLive","indices":[29,37]}],"symbols":[],"user_mentions":[],"urls":[]},"truncated":false,"metadata":{"iso_language_code":"nl","result_type":"recent"},"source":"\u003ca href=\"http:\/\/twitter.com\" rel=\"nofollow\"\u003eTwitter Web Client\u003c\/a\u003e","in_reply_to_status_id":null,"in_reply_to_status_id_str":null,"in_reply_to_user_id":null,"in_reply_to_user_id_str":null,"in_reply_to_screen_name":null,"user":{"id":22910295,"id_str":"22910295","name":"Chelsea FC","screen_name":"ChelseaFC","location":"London, England","description":"The official Twitter account of Premier League champions Chelsea FC. For enquiries visit: https:\/\/t.co\/6AE0WNqdOH","url":"https:\/\/t.co\/7dGFqETrL0","entities":{"url":{"urls":[{"url":"https:\/\/t.co\/7dGFqETrL0","expanded_url":"http:\/\/www.chelseafc.com","display_url":"chelseafc.com","indices":[0,23]}]},"description":{"urls":[{"url":"https:\/\/t.co\/6AE0WNqdOH","expanded_url":"http:\/\/che.lc\/iBt6ES","display_url":"che.lc\/iBt6ES","indices":[90,113]}]}},"protected":false,"followers_count":6745468,"friends_count":229,"listed_count":19627,"created_at":"Thu Mar 05 11:54:25 +0000 2009","favourites_count":10017,"utc_offset":3600,"time_zone":"London","geo_enabled":true,"verified":true,"statuses_count":57848,"lang":"en","contributors_enabled":false,"is_translator":false,"is_translation_enabled":true,"profile_background_color":"023F84","profile_background_image_url":"http:\/\/pbs.twimg.com\/profile_background_images\/636517723892252672\/DUnOnH-G.jpg","profile_background_image_url_https":"https:\/\/pbs.twimg.com\/profile_background_images\/636517723892252672\/DUnOnH-G.jpg","profile_background_tile":false,"profile_image_url":"http:\/\/pbs.twimg.com\/profile_images\/668322198537531392\/9BcEHF15_normal.jpg","profile_image_url_https":"https:\/\/pbs.twimg.com\/profile_images\/668322198537531392\/9BcEHF15_normal.jpg","profile_banner_url":"https:\/\/pbs.twimg.com\/profile_banners\/22910295\/1457103014","profile_link_color":"375EF1","profile_sidebar_border_color":"FFFFFF","profile_sidebar_fill_color":"37D3FA","profile_text_color":"000000","profile_use_background_image":true,"has_extended_profile":false,"default_profile":false,"default_profile_image":false,"following":false,"follow_request_sent":false,"notifications":false},"geo":null,"coordinates":null,"place":null,"contributors":null,"is_quote_status":false,"retweet_count":2460,"favorite_count":1364,"favorited":false,"retweeted":false,"lang":"nl"},"is_quote_status":false,"retweet_count":2460,"favorite_count":0,"favorited":false,"retweeted":false,"lang":"nl"},{"created_at":"Sat Apr 02 12:13:48 +0000 2016","id":716237191500804097,"id_str":"716237191500804097","text":"RT @ChelseaFC: Great goal; Pato found Mikel who played it on to Pedro. He switched it out to the advancing Azpilicueta and Loftus-Cheek fin\u2026","entities":{"hashtags":[{"text":"CFCLive","indices":[139,140]}],"symbols":[],"user_mentions":[{"screen_name":"ChelseaFC","name":"Chelsea FC","id":22910295,"id_str":"22910295","indices":[3,13]}],"urls":[]},"truncated":false,"metadata":{"iso_language_code":"en","result_type":"recent"},"source":"\u003ca href=\"http:\/\/twitter.com\/download\/android\" rel=\"nofollow\"\u003eTwitter for Android\u003c\/a\u003e","in_reply_to_status_id":null,"in_reply_to_status_id_str":null,"in_reply_to_user_id":null,"in_reply_to_user_id_str":null,"in_reply_to_screen_name":null,"user":{"id":2914664388,"id_str":"2914664388","name":"JIMMY GINTING","screen_name":"ginting_jimmy","location":"Republic of Indonesia","description":"When you're @ChelseaFC #therewillbehaters #KTBFFH #MM93 #ForzaMilan","url":null,"entities":{"description":{"urls":[]}},"protected":false,"followers_count":2083,"friends_count":346,"listed_count":2,"created_at":"Sun Nov 30 12:16:15 +0000 2014","favourites_count":119,"utc_offset":null,"time_zone":null,"geo_enabled":false,"verified":false,"statuses_count":7012,"lang":"id","contributors_enabled":false,"is_translator":false,"is_translation_enabled":false,"profile_background_color":"0099B9","profile_background_image_url":"http:\/\/abs.twimg.com\/images\/themes\/theme4\/bg.gif","profile_background_image_url_https":"https:\/\/abs.twimg.com\/images\/themes\/theme4\/bg.gif","profile_background_tile":false,"profile_image_url":"http:\/\/pbs.twimg.com\/profile_images\/696975280678678528\/ACdsotLx_normal.jpg","profile_image_url_https":"https:\/\/pbs.twimg.com\/profile_images\/696975280678678528\/ACdsotLx_normal.jpg","profile_banner_url":"https:\/\/pbs.twimg.com\/profile_banners\/2914664388\/1434202962","profile_link_color":"0099B9","profile_sidebar_border_color":"5ED4DC","profile_sidebar_fill_color":"95E8EC","profile_text_color":"3C3940","profile_use_background_image":true,"has_extended_profile":false,"default_profile":false,"default_profile_image":false,"following":false,"follow_request_sent":false,"notifications":false},"geo":null,"coordinates":null,"place":null,"contributors":null,"retweeted_status":{"created_at":"Sat Apr 02 12:12:07 +0000 2016","id":716236771152031748,"id_str":"716236771152031748","text":"Great goal; Pato found Mikel who played it on to Pedro. He switched it out to the advancing Azpilicueta and Loftus-Cheek finished. #CFCLive","entities":{"hashtags":[{"text":"CFCLive","indices":[131,139]}],"symbols":[],"user_mentions":[],"urls":[]},"truncated":false,"metadata":{"iso_language_code":"en","result_type":"recent"},"source":"\u003ca href=\"http:\/\/twitter.com\" rel=\"nofollow\"\u003eTwitter Web Client\u003c\/a\u003e","in_reply_to_status_id":null,"in_reply_to_status_id_str":null,"in_reply_to_user_id":null,"in_reply_to_user_id_str":null,"in_reply_to_screen_name":null,"user":{"id":22910295,"id_str":"22910295","name":"Chelsea FC","screen_name":"ChelseaFC","location":"London, England","description":"The official Twitter account of Premier League champions Chelsea FC. For enquiries visit: https:\/\/t.co\/6AE0WNqdOH","url":"https:\/\/t.co\/7dGFqETrL0","entities":{"url":{"urls":[{"url":"https:\/\/t.co\/7dGFqETrL0","expanded_url":"http:\/\/www.chelseafc.com","display_url":"chelseafc.com","indices":[0,23]}]},"description":{"urls":[{"url":"https:\/\/t.co\/6AE0WNqdOH","expanded_url":"http:\/\/che.lc\/iBt6ES","display_url":"che.lc\/iBt6ES","indices":[90,113]}]}},"protected":false,"followers_count":6745468,"friends_count":229,"listed_count":19627,"created_at":"Thu Mar 05 11:54:25 +0000 2009","favourites_count":10017,"utc_offset":3600,"time_zone":"London","geo_enabled":true,"verified":true,"statuses_count":57848,"lang":"en","contributors_enabled":false,"is_translator":false,"is_translation_enabled":true,"profile_background_color":"023F84","profile_background_image_url":"http:\/\/pbs.twimg.com\/profile_background_images\/636517723892252672\/DUnOnH-G.jpg","profile_background_image_url_https":"https:\/\/pbs.twimg.com\/profile_background_images\/636517723892252672\/DUnOnH-G.jpg","profile_background_tile":false,"profile_image_url":"http:\/\/pbs.twimg.com\/profile_images\/668322198537531392\/9BcEHF15_normal.jpg","profile_image_url_https":"https:\/\/pbs.twimg.com\/profile_images\/668322198537531392\/9BcEHF15_normal.jpg","profile_banner_url":"https:\/\/pbs.twimg.com\/profile_banners\/22910295\/1457103014","profile_link_color":"375EF1","profile_sidebar_border_color":"FFFFFF","profile_sidebar_fill_color":"37D3FA","profile_text_color":"000000","profile_use_background_image":true,"has_extended_profile":false,"default_profile":false,"default_profile_image":false,"following":false,"follow_request_sent":false,"notifications":false},"geo":null,"coordinates":null,"place":null,"contributors":null,"is_quote_status":false,"retweet_count":606,"favorite_count":552,"favorited":false,"retweeted":false,"lang":"en"},"is_quote_status":false,"retweet_count":606,"favorite_count":0,"favorited":false,"retweeted":false,"lang":"en"},{"created_at":"Sat Apr 02 12:13:47 +0000 2016","id":716237190146162688,"id_str":"716237190146162688","text":"RT @ChelseaFC: Great goal; Pato found Mikel who played it on to Pedro. He switched it out to the advancing Azpilicueta and Loftus-Cheek fin\u2026","entities":{"hashtags":[{"text":"CFCLive","indices":[139,140]}],"symbols":[],"user_mentions":[{"screen_name":"ChelseaFC","name":"Chelsea FC","id":22910295,"id_str":"22910295","indices":[3,13]}],"urls":[]},"truncated":false,"metadata":{"iso_language_code":"en","result_type":"recent"},"source":"\u003ca href=\"http:\/\/www.twitter.com\" rel=\"nofollow\"\u003eTwitter for BlackBerry\u003c\/a\u003e","in_reply_to_status_id":null,"in_reply_to_status_id_str":null,"in_reply_to_user_id":null,"in_reply_to_user_id_str":null,"in_reply_to_screen_name":null,"user":{"id":175711786,"id_str":"175711786","name":"EYEN AKWAIBOM","screen_name":"veeveerich","location":"ZION","description":"Director (PRO - VIEW LTD).Real Estate,  PR, Branding, Events Management & Planning.  Follow @Pro_viewltd | \u007bCrazy & Addicted to Christ\u007d. I'M IBIBIO","url":null,"entities":{"description":{"urls":[]}},"protected":false,"followers_count":1141,"friends_count":718,"listed_count":32,"created_at":"Sat Aug 07 11:15:35 +0000 2010","favourites_count":329,"utc_offset":null,"time_zone":null,"geo_enabled":true,"verified":false,"statuses_count":64130,"lang":"en","contributors_enabled":false,"is_translator":false,"is_translation_enabled":false,"profile_background_color":"C0DEED","profile_background_image_url":"http:\/\/abs.twimg.com\/images\/themes\/theme1\/bg.png","profile_background_image_url_https":"https:\/\/abs.twimg.com\/images\/themes\/theme1\/bg.png","profile_background_tile":false,"profile_image_url":"http:\/\/pbs.twimg.com\/profile_images\/713482841208791041\/eqF2HasJ_normal.jpg","profile_image_url_https":"https:\/\/pbs.twimg.com\/profile_images\/713482841208791041\/eqF2HasJ_normal.jpg","profile_banner_url":"https:\/\/pbs.twimg.com\/profile_banners\/175711786\/1458942533","profile_link_color":"0084B4","profile_sidebar_border_color":"C0DEED","profile_sidebar_fill_color":"DDEEF6","profile_text_color":"333333","profile_use_background_image":true,"has_extended_profile":false,"default_profile":true,"default_profile_image":false,"following":false,"follow_request_sent":false,"notifications":false},"geo":null,"coordinates":null,"place":null,"contributors":null,"retweeted_status":{"created_at":"Sat Apr 02 12:12:07 +0000 2016","id":716236771152031748,"id_str":"716236771152031748","text":"Great goal; Pato found Mikel who played it on to Pedro. He switched it out to the advancing Azpilicueta and Loftus-Cheek finished. #CFCLive","entities":{"hashtags":[{"text":"CFCLive","indices":[131,139]}],"symbols":[],"user_mentions":[],"urls":[]},"truncated":false,"metadata":{"iso_language_code":"en","result_type":"recent"},"source":"\u003ca href=\"http:\/\/twitter.com\" rel=\"nofollow\"\u003eTwitter Web Client\u003c\/a\u003e","in_reply_to_status_id":null,"in_reply_to_status_id_str":null,"in_reply_to_user_id":null,"in_reply_to_user_id_str":null,"in_reply_to_screen_name":null,"user":{"id":22910295,"id_str":"22910295","name":"Chelsea FC","screen_name":"ChelseaFC","location":"London, England","description":"The official Twitter account of Premier League champions Chelsea FC. For enquiries visit: https:\/\/t.co\/6AE0WNqdOH","url":"https:\/\/t.co\/7dGFqETrL0","entities":{"url":{"urls":[{"url":"https:\/\/t.co\/7dGFqETrL0","expanded_url":"http:\/\/www.chelseafc.com","display_url":"chelseafc.com","indices":[0,23]}]},"description":{"urls":[{"url":"https:\/\/t.co\/6AE0WNqdOH","expanded_url":"http:\/\/che.lc\/iBt6ES","display_url":"che.lc\/iBt6ES","indices":[90,113]}]}},"protected":false,"followers_count":6745468,"friends_count":229,"listed_count":19627,"created_at":"Thu Mar 05 11:54:25 +0000 2009","favourites_count":10017,"utc_offset":3600,"time_zone":"London","geo_enabled":true,"verified":true,"statuses_count":57848,"lang":"en","contributors_enabled":false,"is_translator":false,"is_translation_enabled":true,"profile_background_color":"023F84","profile_background_image_url":"http:\/\/pbs.twimg.com\/profile_background_images\/636517723892252672\/DUnOnH-G.jpg","profile_background_image_url_https":"https:\/\/pbs.twimg.com\/profile_background_images\/636517723892252672\/DUnOnH-G.jpg","profile_background_tile":false,"profile_image_url":"http:\/\/pbs.twimg.com\/profile_images\/668322198537531392\/9BcEHF15_normal.jpg","profile_image_url_https":"https:\/\/pbs.twimg.com\/profile_images\/668322198537531392\/9BcEHF15_normal.jpg","profile_banner_url":"https:\/\/pbs.twimg.com\/profile_banners\/22910295\/1457103014","profile_link_color":"375EF1","profile_sidebar_border_color":"FFFFFF","profile_sidebar_fill_color":"37D3FA","profile_text_color":"000000","profile_use_background_image":true,"has_extended_profile":false,"default_profile":false,"default_profile_image":false,"following":false,"follow_request_sent":false,"notifications":false},"geo":null,"coordinates":null,"place":null,"contributors":null,"is_quote_status":false,"retweet_count":606,"favorite_count":552,"favorited":false,"retweeted":false,"lang":"en"},"is_quote_status":false,"retweet_count":606,"favorite_count":0,"favorited":false,"retweeted":false,"lang":"en"},{"created_at":"Sat Apr 02 12:13:47 +0000 2016","id":716237189986721792,"id_str":"716237189986721792","text":"RT @ChelseaFC: GOAL!!! 1-0, Loftus-Cheek!!! #CFCLive","entities":{"hashtags":[{"text":"CFCLive","indices":[44,52]}],"symbols":[],"user_mentions":[{"screen_name":"ChelseaFC","name":"Chelsea FC","id":22910295,"id_str":"22910295","indices":[3,13]}],"urls":[]},"truncated":false,"metadata":{"iso_language_code":"nl","result_type":"recent"},"source":"\u003ca href=\"http:\/\/twitter.com\/download\/android\" rel=\"nofollow\"\u003eTwitter for Android\u003c\/a\u003e","in_reply_to_status_id":null,"in_reply_to_status_id_str":null,"in_reply_to_user_id":null,"in_reply_to_user_id_str":null,"in_reply_to_screen_name":null,"user":{"id":372296359,"id_str":"372296359","name":"WALDORF\u2665","screen_name":"CarmenGomez34","location":"","description":"I'm a bitch with wifi.","url":null,"entities":{"description":{"urls":[]}},"protected":false,"followers_count":706,"friends_count":495,"listed_count":3,"created_at":"Mon Sep 12 14:25:17 +0000 2011","favourites_count":747,"utc_offset":null,"time_zone":null,"geo_enabled":false,"verified":false,"statuses_count":21661,"lang":"es","contributors_enabled":false,"is_translator":false,"is_translation_enabled":false,"profile_background_color":"05A2F0","profile_background_image_url":"http:\/\/pbs.twimg.com\/profile_background_images\/587009958534721536\/x50-xjue.jpg","profile_background_image_url_https":"https:\/\/pbs.twimg.com\/profile_background_images\/587009958534721536\/x50-xjue.jpg","profile_background_tile":true,"profile_image_url":"http:\/\/pbs.twimg.com\/profile_images\/693130326990819329\/XYTJEJHZ_normal.jpg","profile_image_url_https":"https:\/\/pbs.twimg.com\/profile_images\/693130326990819329\/XYTJEJHZ_normal.jpg","profile_banner_url":"https:\/\/pbs.twimg.com\/profile_banners\/372296359\/1455229872","profile_link_color":"1CEB09","profile_sidebar_border_color":"000000","profile_sidebar_fill_color":"DDEEF6","profile_text_color":"333333","profile_use_background_image":true,"has_extended_profile":true,"default_profile":false,"default_profile_image":false,"following":false,"follow_request_sent":false,"notifications":false},"geo":null,"coordinates":null,"place":null,"contributors":null,"retweeted_status":{"created_at":"Sat Apr 02 12:10:53 +0000 2016","id":716236460341534720,"id_str":"716236460341534720","text":"GOAL!!! 1-0, Loftus-Cheek!!! #CFCLive","entities":{"hashtags":[{"text":"CFCLive","indices":[29,37]}],"symbols":[],"user_mentions":[],"urls":[]},"truncated":false,"metadata":{"iso_language_code":"nl","result_type":"recent"},"source":"\u003ca href=\"http:\/\/twitter.com\" rel=\"nofollow\"\u003eTwitter Web Client\u003c\/a\u003e","in_reply_to_status_id":null,"in_reply_to_status_id_str":null,"in_reply_to_user_id":null,"in_reply_to_user_id_str":null,"in_reply_to_screen_name":null,"user":{"id":22910295,"id_str":"22910295","name":"Chelsea FC","screen_name":"ChelseaFC","location":"London, England","description":"The official Twitter account of Premier League champions Chelsea FC. For enquiries visit: https:\/\/t.co\/6AE0WNqdOH","url":"https:\/\/t.co\/7dGFqETrL0","entities":{"url":{"urls":[{"url":"https:\/\/t.co\/7dGFqETrL0","expanded_url":"http:\/\/www.chelseafc.com","display_url":"chelseafc.com","indices":[0,23]}]},"description":{"urls":[{"url":"https:\/\/t.co\/6AE0WNqdOH","expanded_url":"http:\/\/che.lc\/iBt6ES","display_url":"che.lc\/iBt6ES","indices":[90,113]}]}},"protected":false,"followers_count":6745468,"friends_count":229,"listed_count":19627,"created_at":"Thu Mar 05 11:54:25 +0000 2009","favourites_count":10017,"utc_offset":3600,"time_zone":"London","geo_enabled":true,"verified":true,"statuses_count":57848,"lang":"en","contributors_enabled":false,"is_translator":false,"is_translation_enabled":true,"profile_background_color":"023F84","profile_background_image_url":"http:\/\/pbs.twimg.com\/profile_background_images\/636517723892252672\/DUnOnH-G.jpg","profile_background_image_url_https":"https:\/\/pbs.twimg.com\/profile_background_images\/636517723892252672\/DUnOnH-G.jpg","profile_background_tile":false,"profile_image_url":"http:\/\/pbs.twimg.com\/profile_images\/668322198537531392\/9BcEHF15_normal.jpg","profile_image_url_https":"https:\/\/pbs.twimg.com\/profile_images\/668322198537531392\/9BcEHF15_normal.jpg","profile_banner_url":"https:\/\/pbs.twimg.com\/profile_banners\/22910295\/1457103014","profile_link_color":"375EF1","profile_sidebar_border_color":"FFFFFF","profile_sidebar_fill_color":"37D3FA","profile_text_color":"000000","profile_use_background_image":true,"has_extended_profile":false,"default_profile":false,"default_profile_image":false,"following":false,"follow_request_sent":false,"notifications":false},"geo":null,"coordinates":null,"place":null,"contributors":null,"is_quote_status":false,"retweet_count":2460,"favorite_count":1364,"favorited":false,"retweeted":false,"lang":"nl"},"is_quote_status":false,"retweet_count":2460,"favorite_count":0,"favorited":false,"retweeted":false,"lang":"nl"},{"created_at":"Sat Apr 02 12:13:47 +0000 2016","id":716237189970071554,"id_str":"716237189970071554","text":"RT @ChelseaFC: Pato is wearing the No.11 shirt for the Blues. #CFCLive","entities":{"hashtags":[{"text":"CFCLive","indices":[62,70]}],"symbols":[],"user_mentions":[{"screen_name":"ChelseaFC","name":"Chelsea FC","id":22910295,"id_str":"22910295","indices":[3,13]}],"urls":[]},"truncated":false,"metadata":{"iso_language_code":"en","result_type":"recent"},"source":"\u003ca href=\"http:\/\/twitter.com\/download\/android\" rel=\"nofollow\"\u003eTwitter for Android\u003c\/a\u003e","in_reply_to_status_id":null,"in_reply_to_status_id_str":null,"in_reply_to_user_id":null,"in_reply_to_user_id_str":null,"in_reply_to_screen_name":null,"user":{"id":586013300,"id_str":"586013300","name":"Edward","screen_name":"edwardibia","location":"Lagos,Nigeria ","description":".......dentist.......","url":null,"entities":{"description":{"urls":[]}},"protected":false,"followers_count":713,"friends_count":472,"listed_count":9,"created_at":"Sun May 20 21:36:57 +0000 2012","favourites_count":130,"utc_offset":null,"time_zone":null,"geo_enabled":true,"verified":false,"statuses_count":26396,"lang":"en","contributors_enabled":false,"is_translator":false,"is_translation_enabled":false,"profile_background_color":"C0DEED","profile_background_image_url":"http:\/\/abs.twimg.com\/images\/themes\/theme1\/bg.png","profile_background_image_url_https":"https:\/\/abs.twimg.com\/images\/themes\/theme1\/bg.png","profile_background_tile":false,"profile_image_url":"http:\/\/pbs.twimg.com\/profile_images\/694313881821417473\/G6F7jbyZ_normal.jpg","profile_image_url_https":"https:\/\/pbs.twimg.com\/profile_images\/694313881821417473\/G6F7jbyZ_normal.jpg","profile_banner_url":"https:\/\/pbs.twimg.com\/profile_banners\/586013300\/1457891783","profile_link_color":"0084B4","profile_sidebar_border_color":"C0DEED","profile_sidebar_fill_color":"DDEEF6","profile_text_color":"333333","profile_use_background_image":true,"has_extended_profile":false,"default_profile":true,"default_profile_image":false,"following":false,"follow_request_sent":false,"notifications":false},"geo":null,"coordinates":null,"place":null,"contributors":null,"retweeted_status":{"created_at":"Sat Apr 02 12:09:59 +0000 2016","id":716236231290580992,"id_str":"716236231290580992","text":"Pato is wearing the No.11 shirt for the Blues. #CFCLive","entities":{"hashtags":[{"text":"CFCLive","indices":[47,55]}],"symbols":[],"user_mentions":[],"urls":[]},"truncated":false,"metadata":{"iso_language_code":"en","result_type":"recent"},"source":"\u003ca href=\"http:\/\/twitter.com\" rel=\"nofollow\"\u003eTwitter Web Client\u003c\/a\u003e","in_reply_to_status_id":null,"in_reply_to_status_id_str":null,"in_reply_to_user_id":null,"in_reply_to_user_id_str":null,"in_reply_to_screen_name":null,"user":{"id":22910295,"id_str":"22910295","name":"Chelsea FC","screen_name":"ChelseaFC","location":"London, England","description":"The official Twitter account of Premier League champions Chelsea FC. For enquiries visit: https:\/\/t.co\/6AE0WNqdOH","url":"https:\/\/t.co\/7dGFqETrL0","entities":{"url":{"urls":[{"url":"https:\/\/t.co\/7dGFqETrL0","expanded_url":"http:\/\/www.chelseafc.com","display_url":"chelseafc.com","indices":[0,23]}]},"description":{"urls":[{"url":"https:\/\/t.co\/6AE0WNqdOH","expanded_url":"http:\/\/che.lc\/iBt6ES","display_url":"che.lc\/iBt6ES","indices":[90,113]}]}},"protected":false,"followers_count":6745468,"friends_count":229,"listed_count":19627,"created_at":"Thu Mar 05 11:54:25 +0000 2009","favourites_count":10017,"utc_offset":3600,"time_zone":"London","geo_enabled":true,"verified":true,"statuses_count":57848,"lang":"en","contributors_enabled":false,"is_translator":false,"is_translation_enabled":true,"profile_background_color":"023F84","profile_background_image_url":"http:\/\/pbs.twimg.com\/profile_background_images\/636517723892252672\/DUnOnH-G.jpg","profile_background_image_url_https":"https:\/\/pbs.twimg.com\/profile_background_images\/636517723892252672\/DUnOnH-G.jpg","profile_background_tile":false,"profile_image_url":"http:\/\/pbs.twimg.com\/profile_images\/668322198537531392\/9BcEHF15_normal.jpg","profile_image_url_https":"https:\/\/pbs.twimg.com\/profile_images\/668322198537531392\/9BcEHF15_normal.jpg","profile_banner_url":"https:\/\/pbs.twimg.com\/profile_banners\/22910295\/1457103014","profile_link_color":"375EF1","profile_sidebar_border_color":"FFFFFF","profile_sidebar_fill_color":"37D3FA","profile_text_color":"000000","profile_use_background_image":true,"has_extended_profile":false,"default_profile":false,"default_profile_image":false,"following":false,"follow_request_sent":false,"notifications":false},"geo":null,"coordinates":null,"place":null,"contributors":null,"is_quote_status":false,"retweet_count":696,"favorite_count":532,"favorited":false,"retweeted":false,"lang":"en"},"is_quote_status":false,"retweet_count":696,"favorite_count":0,"favorited":false,"retweeted":false,"lang":"en"},{"created_at":"Sat Apr 02 12:13:47 +0000 2016","id":716237189848375296,"id_str":"716237189848375296","text":"RT @ChelseaFC: That's Loftus-Cheek's first Premier League goal and it's well deserved after a bright start. #CFCLive","entities":{"hashtags":[{"text":"CFCLive","indices":[108,116]}],"symbols":[],"user_mentions":[{"screen_name":"ChelseaFC","name":"Chelsea FC","id":22910295,"id_str":"22910295","indices":[3,13]}],"urls":[]},"truncated":false,"metadata":{"iso_language_code":"en","result_type":"recent"},"source":"\u003ca href=\"http:\/\/twitter.com\/download\/android\" rel=\"nofollow\"\u003eTwitter for Android\u003c\/a\u003e","in_reply_to_status_id":null,"in_reply_to_status_id_str":null,"in_reply_to_user_id":null,"in_reply_to_user_id_str":null,"in_reply_to_screen_name":null,"user":{"id":234649591,"id_str":"234649591","name":"Naveed Parkar","screen_name":"SilentlyAmused","location":"Navi Mumbai, Maharashtra","description":"I Don't Do Subtle! :) #CFC #MI","url":"https:\/\/t.co\/yHmQyMDy8z","entities":{"url":{"urls":[{"url":"https:\/\/t.co\/yHmQyMDy8z","expanded_url":"http:\/\/instagram.com\/naveedparkar","display_url":"instagram.com\/naveedparkar","indices":[0,23]}]},"description":{"urls":[]}},"protected":false,"followers_count":827,"friends_count":311,"listed_count":21,"created_at":"Thu Jan 06 06:08:30 +0000 2011","favourites_count":4509,"utc_offset":19800,"time_zone":"New Delhi","geo_enabled":true,"verified":false,"statuses_count":33311,"lang":"en","contributors_enabled":false,"is_translator":false,"is_translation_enabled":false,"profile_background_color":"020D12","profile_background_image_url":"http:\/\/pbs.twimg.com\/profile_background_images\/803980119\/8ca9c963404b0dea4d5657589dc7dc70.jpeg","profile_background_image_url_https":"https:\/\/pbs.twimg.com\/profile_background_images\/803980119\/8ca9c963404b0dea4d5657589dc7dc70.jpeg","profile_background_tile":false,"profile_image_url":"http:\/\/pbs.twimg.com\/profile_images\/425532758908084224\/krIYHbG4_normal.jpeg","profile_image_url_https":"https:\/\/pbs.twimg.com\/profile_images\/425532758908084224\/krIYHbG4_normal.jpeg","profile_banner_url":"https:\/\/pbs.twimg.com\/profile_banners\/234649591\/1435486348","profile_link_color":"3B94D9","profile_sidebar_border_color":"FFFFFF","profile_sidebar_fill_color":"DDEEF6","profile_text_color":"333333","profile_use_background_image":true,"has_extended_profile":true,"default_profile":false,"default_profile_image":false,"following":false,"follow_request_sent":false,"notifications":false},"geo":null,"coordinates":null,"place":null,"contributors":null,"retweeted_status":{"created_at":"Sat Apr 02 12:12:54 +0000 2016","id":716236967646732288,"id_str":"716236967646732288","text":"That's Loftus-Cheek's first Premier League goal and it's well deserved after a bright start. #CFCLive","entities":{"hashtags":[{"text":"CFCLive","indices":[93,101]}],"symbols":[],"user_mentions":[],"urls":[]},"truncated":false,"metadata":{"iso_language_code":"en","result_type":"recent"},"source":"\u003ca href=\"http:\/\/twitter.com\" rel=\"nofollow\"\u003eTwitter Web Client\u003c\/a\u003e","in_reply_to_status_id":null,"in_reply_to_status_id_str":null,"in_reply_to_user_id":null,"in_reply_to_user_id_str":null,"in_reply_to_screen_name":null,"user":{"id":22910295,"id_str":"22910295","name":"Chelsea FC","screen_name":"ChelseaFC","location":"London, England","description":"The official Twitter account of Premier League champions Chelsea FC. For enquiries visit: https:\/\/t.co\/6AE0WNqdOH","url":"https:\/\/t.co\/7dGFqETrL0","entities":{"url":{"urls":[{"url":"https:\/\/t.co\/7dGFqETrL0","expanded_url":"http:\/\/www.chelseafc.com","display_url":"chelseafc.com","indices":[0,23]}]},"description":{"urls":[{"url":"https:\/\/t.co\/6AE0WNqdOH","expanded_url":"http:\/\/che.lc\/iBt6ES","display_url":"che.lc\/iBt6ES","indices":[90,113]}]}},"protected":false,"followers_count":6745468,"friends_count":229,"listed_count":19627,"created_at":"Thu Mar 05 11:54:25 +0000 2009","favourites_count":10017,"utc_offset":3600,"time_zone":"London","geo_enabled":true,"verified":true,"statuses_count":57848,"lang":"en","contributors_enabled":false,"is_translator":false,"is_translation_enabled":true,"profile_background_color":"023F84","profile_background_image_url":"http:\/\/pbs.twimg.com\/profile_background_images\/636517723892252672\/DUnOnH-G.jpg","profile_background_image_url_https":"https:\/\/pbs.twimg.com\/profile_background_images\/636517723892252672\/DUnOnH-G.jpg","profile_background_tile":false,"profile_image_url":"http:\/\/pbs.twimg.com\/profile_images\/668322198537531392\/9BcEHF15_normal.jpg","profile_image_url_https":"https:\/\/pbs.twimg.com\/profile_images\/668322198537531392\/9BcEHF15_normal.jpg","profile_banner_url":"https:\/\/pbs.twimg.com\/profile_banners\/22910295\/1457103014","profile_link_color":"375EF1","profile_sidebar_border_color":"FFFFFF","profile_sidebar_fill_color":"37D3FA","profile_text_color":"000000","profile_use_background_image":true,"has_extended_profile":false,"default_profile":false,"default_profile_image":false,"following":false,"follow_request_sent":false,"notifications":false},"geo":null,"coordinates":null,"place":null,"contributors":null,"is_quote_status":false,"retweet_count":487,"favorite_count":495,"favorited":false,"retweeted":false,"lang":"en"},"is_quote_status":false,"retweet_count":487,"favorite_count":0,"favorited":false,"retweeted":false,"lang":"en"},{"created_at":"Sat Apr 02 12:13:47 +0000 2016","id":716237189433200641,"id_str":"716237189433200641","text":"GOAL Aston Villa 0-1 Chelsea (26 mins). Azpilicueta finds Loftus-Cheek in the box and his shot is deflected in off Lescott #AVLCHE","entities":{"hashtags":[{"text":"AVLCHE","indices":[123,130]}],"symbols":[],"user_mentions":[],"urls":[]},"truncated":false,"metadata":{"iso_language_code":"en","result_type":"recent"},"source":"\u003ca href=\"https:\/\/mobile.twitter.com\" rel=\"nofollow\"\u003eMobile Web (M2)\u003c\/a\u003e","in_reply_to_status_id":null,"in_reply_to_status_id_str":null,"in_reply_to_user_id":null,"in_reply_to_user_id_str":null,"in_reply_to_screen_name":null,"user":{"id":3241518441,"id_str":"3241518441","name":"TVAfricasports","screen_name":"tvafricasports","location":"Accra, Ghana","description":"This is the official twiiter handle for Tv Africa sports. You can follow for all the sports updates. Please subscribe on https:\/\/t.co\/h6SZG9zTzb","url":"https:\/\/t.co\/BcA4QXA7Sa","entities":{"url":{"urls":[{"url":"https:\/\/t.co\/BcA4QXA7Sa","expanded_url":"http:\/\/www.tvafricaonline.com","display_url":"tvafricaonline.com","indices":[0,23]}]},"description":{"urls":[{"url":"https:\/\/t.co\/h6SZG9zTzb","expanded_url":"http:\/\/youtube.com\/tvafricasports","display_url":"youtube.com\/tvafricasports","indices":[121,144]}]}},"protected":false,"followers_count":405,"friends_count":244,"listed_count":0,"created_at":"Fri May 08 07:13:58 +0000 2015","favourites_count":5,"utc_offset":-25200,"time_zone":"Pacific Time (US & Canada)","geo_enabled":false,"verified":false,"statuses_count":1811,"lang":"en","contributors_enabled":false,"is_translator":false,"is_translation_enabled":false,"profile_background_color":"C0DEED","profile_background_image_url":"http:\/\/pbs.twimg.com\/profile_background_images\/596583083513524225\/RAbQnPBj.jpg","profile_background_image_url_https":"https:\/\/pbs.twimg.com\/profile_background_images\/596583083513524225\/RAbQnPBj.jpg","profile_background_tile":true,"profile_image_url":"http:\/\/pbs.twimg.com\/profile_images\/596580245991399424\/fJo2QYjy_normal.png","profile_image_url_https":"https:\/\/pbs.twimg.com\/profile_images\/596580245991399424\/fJo2QYjy_normal.png","profile_banner_url":"https:\/\/pbs.twimg.com\/profile_banners\/3241518441\/1441835331","profile_link_color":"FA743E","profile_sidebar_border_color":"C0DEED","profile_sidebar_fill_color":"DDEEF6","profile_text_color":"333333","profile_use_background_image":true,"has_extended_profile":true,"default_profile":false,"default_profile_image":false,"following":false,"follow_request_sent":false,"notifications":false},"geo":null,"coordinates":null,"place":null,"contributors":null,"is_quote_status":false,"retweet_count":0,"favorite_count":0,"favorited":false,"retweeted":false,"lang":"en"},{"created_at":"Sat Apr 02 12:13:47 +0000 2016","id":716237189043118080,"id_str":"716237189043118080","text":"RT @ChelseaFC: Pato is wearing the No.11 shirt for the Blues. #CFCLive","entities":{"hashtags":[{"text":"CFCLive","indices":[62,70]}],"symbols":[],"user_mentions":[{"screen_name":"ChelseaFC","name":"Chelsea FC","id":22910295,"id_str":"22910295","indices":[3,13]}],"urls":[]},"truncated":false,"metadata":{"iso_language_code":"en","result_type":"recent"},"source":"\u003ca href=\"http:\/\/twitter.com\" rel=\"nofollow\"\u003eTwitter Web Client\u003c\/a\u003e","in_reply_to_status_id":null,"in_reply_to_status_id_str":null,"in_reply_to_user_id":null,"in_reply_to_user_id_str":null,"in_reply_to_screen_name":null,"user":{"id":189668099,"id_str":"189668099","name":"perin","screen_name":"teustimao","location":" SC","description":"Corinthians e Real Madrid.  99% vagabundo\n\nSNAP: teusperin","url":"https:\/\/t.co\/vHfTg4vPPu","entities":{"url":{"urls":[{"url":"https:\/\/t.co\/vHfTg4vPPu","expanded_url":"http:\/\/instagram.com\/teustimao\/","display_url":"instagram.com\/teustimao\/","indices":[0,23]}]},"description":{"urls":[]}},"protected":false,"followers_count":441,"friends_count":302,"listed_count":8,"created_at":"Sat Sep 11 22:19:06 +0000 2010","favourites_count":757,"utc_offset":-10800,"time_zone":"Brasilia","geo_enabled":true,"verified":false,"statuses_count":103020,"lang":"pt","contributors_enabled":false,"is_translator":false,"is_translation_enabled":false,"profile_background_color":"0D0A0F","profile_background_image_url":"http:\/\/pbs.twimg.com\/profile_background_images\/514576298056765440\/2sEFcUeh.jpeg","profile_background_image_url_https":"https:\/\/pbs.twimg.com\/profile_background_images\/514576298056765440\/2sEFcUeh.jpeg","profile_background_tile":true,"profile_image_url":"http:\/\/pbs.twimg.com\/profile_images\/714191093261332483\/buXWaGDv_normal.jpg","profile_image_url_https":"https:\/\/pbs.twimg.com\/profile_images\/714191093261332483\/buXWaGDv_normal.jpg","profile_banner_url":"https:\/\/pbs.twimg.com\/profile_banners\/189668099\/1431608103","profile_link_color":"002BFF","profile_sidebar_border_color":"000000","profile_sidebar_fill_color":"252429","profile_text_color":"666666","profile_use_background_image":true,"has_extended_profile":true,"default_profile":false,"default_profile_image":false,"following":false,"follow_request_sent":false,"notifications":false},"geo":null,"coordinates":null,"place":null,"contributors":null,"retweeted_status":{"created_at":"Sat Apr 02 12:09:59 +0000 2016","id":716236231290580992,"id_str":"716236231290580992","text":"Pato is wearing the No.11 shirt for the Blues. #CFCLive","entities":{"hashtags":[{"text":"CFCLive","indices":[47,55]}],"symbols":[],"user_mentions":[],"urls":[]},"truncated":false,"metadata":{"iso_language_code":"en","result_type":"recent"},"source":"\u003ca href=\"http:\/\/twitter.com\" rel=\"nofollow\"\u003eTwitter Web Client\u003c\/a\u003e","in_reply_to_status_id":null,"in_reply_to_status_id_str":null,"in_reply_to_user_id":null,"in_reply_to_user_id_str":null,"in_reply_to_screen_name":null,"user":{"id":22910295,"id_str":"22910295","name":"Chelsea FC","screen_name":"ChelseaFC","location":"London, England","description":"The official Twitter account of Premier League champions Chelsea FC. For enquiries visit: https:\/\/t.co\/6AE0WNqdOH","url":"https:\/\/t.co\/7dGFqETrL0","entities":{"url":{"urls":[{"url":"https:\/\/t.co\/7dGFqETrL0","expanded_url":"http:\/\/www.chelseafc.com","display_url":"chelseafc.com","indices":[0,23]}]},"description":{"urls":[{"url":"https:\/\/t.co\/6AE0WNqdOH","expanded_url":"http:\/\/che.lc\/iBt6ES","display_url":"che.lc\/iBt6ES","indices":[90,113]}]}},"protected":false,"followers_count":6745468,"friends_count":229,"listed_count":19627,"created_at":"Thu Mar 05 11:54:25 +0000 2009","favourites_count":10017,"utc_offset":3600,"time_zone":"London","geo_enabled":true,"verified":true,"statuses_count":57848,"lang":"en","contributors_enabled":false,"is_translator":false,"is_translation_enabled":true,"profile_background_color":"023F84","profile_background_image_url":"http:\/\/pbs.twimg.com\/profile_background_images\/636517723892252672\/DUnOnH-G.jpg","profile_background_image_url_https":"https:\/\/pbs.twimg.com\/profile_background_images\/636517723892252672\/DUnOnH-G.jpg","profile_background_tile":false,"profile_image_url":"http:\/\/pbs.twimg.com\/profile_images\/668322198537531392\/9BcEHF15_normal.jpg","profile_image_url_https":"https:\/\/pbs.twimg.com\/profile_images\/668322198537531392\/9BcEHF15_normal.jpg","profile_banner_url":"https:\/\/pbs.twimg.com\/profile_banners\/22910295\/1457103014","profile_link_color":"375EF1","profile_sidebar_border_color":"FFFFFF","profile_sidebar_fill_color":"37D3FA","profile_text_color":"000000","profile_use_background_image":true,"has_extended_profile":false,"default_profile":false,"default_profile_image":false,"following":false,"follow_request_sent":false,"notifications":false},"geo":null,"coordinates":null,"place":null,"contributors":null,"is_quote_status":false,"retweet_count":696,"favorite_count":532,"favorited":false,"retweeted":false,"lang":"en"},"is_quote_status":false,"retweet_count":696,"favorite_count":0,"favorited":false,"retweeted":false,"lang":"en"},{"created_at":"Sat Apr 02 12:13:47 +0000 2016","id":716237188258775040,"id_str":"716237188258775040","text":"RT @premierleague: GOAL Aston Villa 0-1 Chelsea (26 mins). Azpilicueta finds Loftus-Cheek in the box and his shot is deflected in off Lesco\u2026","entities":{"hashtags":[{"text":"AVLCHE","indices":[139,140]}],"symbols":[],"user_mentions":[{"screen_name":"premierleague","name":"Premier League","id":343627165,"id_str":"343627165","indices":[3,17]}],"urls":[]},"truncated":false,"metadata":{"iso_language_code":"en","result_type":"recent"},"source":"\u003ca href=\"http:\/\/twitter.com\/download\/iphone\" rel=\"nofollow\"\u003eTwitter for iPhone\u003c\/a\u003e","in_reply_to_status_id":null,"in_reply_to_status_id_str":null,"in_reply_to_user_id":null,"in_reply_to_user_id_str":null,"in_reply_to_screen_name":null,"user":{"id":593412563,"id_str":"593412563","name":"FELIPE","screen_name":"pheel_lip","location":"Ghana","description":"To infinity and beyond , snapchat:pheel_lip","url":"https:\/\/t.co\/BTO7WmPP5j","entities":{"url":{"urls":[{"url":"https:\/\/t.co\/BTO7WmPP5j","expanded_url":"http:\/\/Instagram.com\/pheel_lip","display_url":"Instagram.com\/pheel_lip","indices":[0,23]}]},"description":{"urls":[]}},"protected":false,"followers_count":1383,"friends_count":395,"listed_count":18,"created_at":"Tue May 29 06:01:47 +0000 2012","favourites_count":4714,"utc_offset":3600,"time_zone":"Casablanca","geo_enabled":true,"verified":false,"statuses_count":36553,"lang":"en","contributors_enabled":false,"is_translator":false,"is_translation_enabled":false,"profile_background_color":"92AA86","profile_background_image_url":"http:\/\/pbs.twimg.com\/profile_background_images\/378800000063322814\/ae4fb943cd13e1717c1df1d6af2dcae3.jpeg","profile_background_image_url_https":"https:\/\/pbs.twimg.com\/profile_background_images\/378800000063322814\/ae4fb943cd13e1717c1df1d6af2dcae3.jpeg","profile_background_tile":true,"profile_image_url":"http:\/\/pbs.twimg.com\/profile_images\/715845030536151042\/Hr-j2lo-_normal.jpg","profile_image_url_https":"https:\/\/pbs.twimg.com\/profile_images\/715845030536151042\/Hr-j2lo-_normal.jpg","profile_banner_url":"https:\/\/pbs.twimg.com\/profile_banners\/593412563\/1459505848","profile_link_color":"DB2E8A","profile_sidebar_border_color":"000000","profile_sidebar_fill_color":"D0BD79","profile_text_color":"D08365","profile_use_background_image":true,"has_extended_profile":true,"default_profile":false,"default_profile_image":false,"following":false,"follow_request_sent":false,"notifications":false},"geo":null,"coordinates":null,"place":null,"contributors":null,"retweeted_status":{"created_at":"Sat Apr 02 12:11:36 +0000 2016","id":716236640197468160,"id_str":"716236640197468160","text":"GOAL Aston Villa 0-1 Chelsea (26 mins). Azpilicueta finds Loftus-Cheek in the box and his shot is deflected in off Lescott #AVLCHE","entities":{"hashtags":[{"text":"AVLCHE","indices":[123,130]}],"symbols":[],"user_mentions":[],"urls":[]},"truncated":false,"metadata":{"iso_language_code":"en","result_type":"recent"},"source":"\u003ca href=\"http:\/\/twitter.com\" rel=\"nofollow\"\u003eTwitter Web Client\u003c\/a\u003e","in_reply_to_status_id":null,"in_reply_to_status_id_str":null,"in_reply_to_user_id":null,"in_reply_to_user_id_str":null,"in_reply_to_screen_name":null,"user":{"id":343627165,"id_str":"343627165","name":"Premier League","screen_name":"premierleague","location":"","description":"Official Twitter account of the Premier League #BPL http:\/\/t.co\/wF29U6HqBW","url":"http:\/\/t.co\/lbJkOEIneJ","entities":{"url":{"urls":[{"url":"http:\/\/t.co\/lbJkOEIneJ","expanded_url":"http:\/\/www.premierleague.com","display_url":"premierleague.com","indices":[0,22]}]},"description":{"urls":[{"url":"http:\/\/t.co\/wF29U6HqBW","expanded_url":"http:\/\/instagram.com\/premierleague","display_url":"instagram.com\/premierleague","indices":[52,74]}]}},"protected":false,"followers_count":11257345,"friends_count":23,"listed_count":18788,"created_at":"Wed Jul 27 21:09:32 +0000 2011","favourites_count":614,"utc_offset":3600,"time_zone":"London","geo_enabled":true,"verified":true,"statuses_count":63967,"lang":"en","contributors_enabled":false,"is_translator":false,"is_translation_enabled":true,"profile_background_color":"050528","profile_background_image_url":"http:\/\/pbs.twimg.com\/profile_background_images\/378800000161701914\/r0W2wiQt.jpeg","profile_background_image_url_https":"https:\/\/pbs.twimg.com\/profile_background_images\/378800000161701914\/r0W2wiQt.jpeg","profile_background_tile":false,"profile_image_url":"http:\/\/pbs.twimg.com\/profile_images\/1466012174\/PL-Twitter-Icon_normal.jpg","profile_image_url_https":"https:\/\/pbs.twimg.com\/profile_images\/1466012174\/PL-Twitter-Icon_normal.jpg","profile_banner_url":"https:\/\/pbs.twimg.com\/profile_banners\/343627165\/1458552904","profile_link_color":"93A644","profile_sidebar_border_color":"FFFFFF","profile_sidebar_fill_color":"171838","profile_text_color":"FFFFFF","profile_use_background_image":false,"has_extended_profile":false,"default_profile":false,"default_profile_image":false,"following":false,"follow_request_sent":false,"notifications":false},"geo":null,"coordinates":null,"place":null,"contributors":null,"is_quote_status":false,"retweet_count":406,"favorite_count":363,"favorited":false,"retweeted":false,"lang":"en"},"is_quote_status":false,"retweet_count":406,"favorite_count":0,"favorited":false,"retweeted":false,"lang":"en"},{"created_at":"Sat Apr 02 12:13:47 +0000 2016","id":716237187428126720,"id_str":"716237187428126720","text":"Fabregas is booked too in the process. #CFCLive #AVLCHE","entities":{"hashtags":[{"text":"CFCLive","indices":[39,47]},{"text":"AVLCHE","indices":[48,55]}],"symbols":[],"user_mentions":[],"urls":[]},"truncated":false,"metadata":{"iso_language_code":"en","result_type":"recent"},"source":"\u003ca href=\"http:\/\/twitter.com\/download\/android\" rel=\"nofollow\"\u003eTwitter for Android\u003c\/a\u003e","in_reply_to_status_id":null,"in_reply_to_status_id_str":null,"in_reply_to_user_id":null,"in_reply_to_user_id_str":null,"in_reply_to_screen_name":null,"user":{"id":113655005,"id_str":"113655005","name":"Chelsea India","screen_name":"ChelseaIndia","location":"India","description":"We are the Official Chelsea India Supporters Club\u2122 affiliated to @chelseafc","url":"http:\/\/t.co\/LWpSDZwC7S","entities":{"url":{"urls":[{"url":"http:\/\/t.co\/LWpSDZwC7S","expanded_url":"http:\/\/www.chelseaindia.com","display_url":"chelseaindia.com","indices":[0,22]}]},"description":{"urls":[]}},"protected":false,"followers_count":9677,"friends_count":242,"listed_count":85,"created_at":"Fri Feb 12 15:16:12 +0000 2010","favourites_count":609,"utc_offset":19800,"time_zone":"Mumbai","geo_enabled":true,"verified":false,"statuses_count":9020,"lang":"en","contributors_enabled":false,"is_translator":false,"is_translation_enabled":false,"profile_background_color":"000000","profile_background_image_url":"http:\/\/pbs.twimg.com\/profile_background_images\/436481404411469825\/ndVgHRyl.jpeg","profile_background_image_url_https":"https:\/\/pbs.twimg.com\/profile_background_images\/436481404411469825\/ndVgHRyl.jpeg","profile_background_tile":false,"profile_image_url":"http:\/\/pbs.twimg.com\/profile_images\/451414904268795906\/UdD8Qj0U_normal.png","profile_image_url_https":"https:\/\/pbs.twimg.com\/profile_images\/451414904268795906\/UdD8Qj0U_normal.png","profile_banner_url":"https:\/\/pbs.twimg.com\/profile_banners\/113655005\/1458997405","profile_link_color":"0042B3","profile_sidebar_border_color":"FFFFFF","profile_sidebar_fill_color":"8A9ACC","profile_text_color":"916565","profile_use_background_image":true,"has_extended_profile":false,"default_profile":false,"default_profile_image":false,"following":false,"follow_request_sent":false,"notifications":false},"geo":null,"coordinates":null,"place":null,"contributors":null,"is_quote_status":false,"retweet_count":0,"favorite_count":1,"favorited":false,"retweeted":false,"lang":"en"},{"created_at":"Sat Apr 02 12:13:47 +0000 2016","id":716237187046645761,"id_str":"716237187046645761","text":"RT @ChelseaFC: Great goal; Pato found Mikel who played it on to Pedro. He switched it out to the advancing Azpilicueta and Loftus-Cheek fin\u2026","entities":{"hashtags":[{"text":"CFCLive","indices":[139,140]}],"symbols":[],"user_mentions":[{"screen_name":"ChelseaFC","name":"Chelsea FC","id":22910295,"id_str":"22910295","indices":[3,13]}],"urls":[]},"truncated":false,"metadata":{"iso_language_code":"en","result_type":"recent"},"source":"\u003ca href=\"http:\/\/twitter.com\" rel=\"nofollow\"\u003eTwitter Web Client\u003c\/a\u003e","in_reply_to_status_id":null,"in_reply_to_status_id_str":null,"in_reply_to_user_id":null,"in_reply_to_user_id_str":null,"in_reply_to_screen_name":null,"user":{"id":511550401,"id_str":"511550401","name":"onyekwere ucheya","screen_name":"onyekwereucheya","location":"","description":"","url":null,"entities":{"description":{"urls":[]}},"protected":false,"followers_count":45,"friends_count":165,"listed_count":0,"created_at":"Fri Mar 02 07:41:12 +0000 2012","favourites_count":6,"utc_offset":null,"time_zone":null,"geo_enabled":false,"verified":false,"statuses_count":240,"lang":"en","contributors_enabled":false,"is_translator":false,"is_translation_enabled":false,"profile_background_color":"C0DEED","profile_background_image_url":"http:\/\/abs.twimg.com\/images\/themes\/theme1\/bg.png","profile_background_image_url_https":"https:\/\/abs.twimg.com\/images\/themes\/theme1\/bg.png","profile_background_tile":false,"profile_image_url":"http:\/\/abs.twimg.com\/sticky\/default_profile_images\/default_profile_5_normal.png","profile_image_url_https":"https:\/\/abs.twimg.com\/sticky\/default_profile_images\/default_profile_5_normal.png","profile_link_color":"0084B4","profile_sidebar_border_color":"C0DEED","profile_sidebar_fill_color":"DDEEF6","profile_text_color":"333333","profile_use_background_image":true,"has_extended_profile":true,"default_profile":true,"default_profile_image":true,"following":false,"follow_request_sent":false,"notifications":false},"geo":null,"coordinates":null,"place":null,"contributors":null,"retweeted_status":{"created_at":"Sat Apr 02 12:12:07 +0000 2016","id":716236771152031748,"id_str":"716236771152031748","text":"Great goal; Pato found Mikel who played it on to Pedro. He switched it out to the advancing Azpilicueta and Loftus-Cheek finished. #CFCLive","entities":{"hashtags":[{"text":"CFCLive","indices":[131,139]}],"symbols":[],"user_mentions":[],"urls":[]},"truncated":false,"metadata":{"iso_language_code":"en","result_type":"recent"},"source":"\u003ca href=\"http:\/\/twitter.com\" rel=\"nofollow\"\u003eTwitter Web Client\u003c\/a\u003e","in_reply_to_status_id":null,"in_reply_to_status_id_str":null,"in_reply_to_user_id":null,"in_reply_to_user_id_str":null,"in_reply_to_screen_name":null,"user":{"id":22910295,"id_str":"22910295","name":"Chelsea FC","screen_name":"ChelseaFC","location":"London, England","description":"The official Twitter account of Premier League champions Chelsea FC. For enquiries visit: https:\/\/t.co\/6AE0WNqdOH","url":"https:\/\/t.co\/7dGFqETrL0","entities":{"url":{"urls":[{"url":"https:\/\/t.co\/7dGFqETrL0","expanded_url":"http:\/\/www.chelseafc.com","display_url":"chelseafc.com","indices":[0,23]}]},"description":{"urls":[{"url":"https:\/\/t.co\/6AE0WNqdOH","expanded_url":"http:\/\/che.lc\/iBt6ES","display_url":"che.lc\/iBt6ES","indices":[90,113]}]}},"protected":false,"followers_count":6745468,"friends_count":229,"listed_count":19627,"created_at":"Thu Mar 05 11:54:25 +0000 2009","favourites_count":10017,"utc_offset":3600,"time_zone":"London","geo_enabled":true,"verified":true,"statuses_count":57848,"lang":"en","contributors_enabled":false,"is_translator":false,"is_translation_enabled":true,"profile_background_color":"023F84","profile_background_image_url":"http:\/\/pbs.twimg.com\/profile_background_images\/636517723892252672\/DUnOnH-G.jpg","profile_background_image_url_https":"https:\/\/pbs.twimg.com\/profile_background_images\/636517723892252672\/DUnOnH-G.jpg","profile_background_tile":false,"profile_image_url":"http:\/\/pbs.twimg.com\/profile_images\/668322198537531392\/9BcEHF15_normal.jpg","profile_image_url_https":"https:\/\/pbs.twimg.com\/profile_images\/668322198537531392\/9BcEHF15_normal.jpg","profile_banner_url":"https:\/\/pbs.twimg.com\/profile_banners\/22910295\/1457103014","profile_link_color":"375EF1","profile_sidebar_border_color":"FFFFFF","profile_sidebar_fill_color":"37D3FA","profile_text_color":"000000","profile_use_background_image":true,"has_extended_profile":false,"default_profile":false,"default_profile_image":false,"following":false,"follow_request_sent":false,"notifications":false},"geo":null,"coordinates":null,"place":null,"contributors":null,"is_quote_status":false,"retweet_count":606,"favorite_count":552,"favorited":false,"retweeted":false,"lang":"en"},"is_quote_status":false,"retweet_count":606,"favorite_count":0,"favorited":false,"retweeted":false,"lang":"en"},{"created_at":"Sat Apr 02 12:13:47 +0000 2016","id":716237186996256769,"id_str":"716237186996256769","text":"RT @ChelseaFC: Pato is about to make his Chelsea debut as Remy is forced off with an early injury. #CFCLive","entities":{"hashtags":[{"text":"CFCLive","indices":[99,107]}],"symbols":[],"user_mentions":[{"screen_name":"ChelseaFC","name":"Chelsea FC","id":22910295,"id_str":"22910295","indices":[3,13]}],"urls":[]},"truncated":false,"metadata":{"iso_language_code":"en","result_type":"recent"},"source":"\u003ca href=\"http:\/\/twitter.com\/download\/iphone\" rel=\"nofollow\"\u003eTwitter for iPhone\u003c\/a\u003e","in_reply_to_status_id":null,"in_reply_to_status_id_str":null,"in_reply_to_user_id":null,"in_reply_to_user_id_str":null,"in_reply_to_screen_name":null,"user":{"id":251265388,"id_str":"251265388","name":"Leticia Vago","screen_name":"_LeticiaVago","location":"London ","description":"18. EDEN HAZARD. CFC. Football \u26bd\ufe0f Brazilian\/Italian. Snapchat: LeehVaago","url":"https:\/\/t.co\/V8Mg30klzD","entities":{"url":{"urls":[{"url":"https:\/\/t.co\/V8Mg30klzD","expanded_url":"https:\/\/Instagram.com\/leticiavago\/","display_url":"Instagram.com\/leticiavago\/","indices":[0,23]}]},"description":{"urls":[]}},"protected":false,"followers_count":5419,"friends_count":572,"listed_count":103,"created_at":"Sat Feb 12 19:47:54 +0000 2011","favourites_count":7520,"utc_offset":3600,"time_zone":"London","geo_enabled":true,"verified":false,"statuses_count":81050,"lang":"en-gb","contributors_enabled":false,"is_translator":false,"is_translation_enabled":false,"profile_background_color":"89C9FA","profile_background_image_url":"http:\/\/pbs.twimg.com\/profile_background_images\/607669251281965056\/9M71RAdY.png","profile_background_image_url_https":"https:\/\/pbs.twimg.com\/profile_background_images\/607669251281965056\/9M71RAdY.png","profile_background_tile":true,"profile_image_url":"http:\/\/pbs.twimg.com\/profile_images\/691349208050352128\/PtNOWpVY_normal.jpg","profile_image_url_https":"https:\/\/pbs.twimg.com\/profile_images\/691349208050352128\/PtNOWpVY_normal.jpg","profile_banner_url":"https:\/\/pbs.twimg.com\/profile_banners\/251265388\/1443814782","profile_link_color":"3B94D9","profile_sidebar_border_color":"FFFFFF","profile_sidebar_fill_color":"FFFFFF","profile_text_color":"000000","profile_use_background_image":true,"has_extended_profile":false,"default_profile":false,"default_profile_image":false,"following":false,"follow_request_sent":false,"notifications":false},"geo":null,"coordinates":null,"place":null,"contributors":null,"retweeted_status":{"created_at":"Sat Apr 02 12:08:11 +0000 2016","id":716235780558073856,"id_str":"716235780558073856","text":"Pato is about to make his Chelsea debut as Remy is forced off with an early injury. #CFCLive","entities":{"hashtags":[{"text":"CFCLive","indices":[84,92]}],"symbols":[],"user_mentions":[],"urls":[]},"truncated":false,"metadata":{"iso_language_code":"en","result_type":"recent"},"source":"\u003ca href=\"http:\/\/twitter.com\" rel=\"nofollow\"\u003eTwitter Web Client\u003c\/a\u003e","in_reply_to_status_id":null,"in_reply_to_status_id_str":null,"in_reply_to_user_id":null,"in_reply_to_user_id_str":null,"in_reply_to_screen_name":null,"user":{"id":22910295,"id_str":"22910295","name":"Chelsea FC","screen_name":"ChelseaFC","location":"London, England","description":"The official Twitter account of Premier League champions Chelsea FC. For enquiries visit: https:\/\/t.co\/6AE0WNqdOH","url":"https:\/\/t.co\/7dGFqETrL0","entities":{"url":{"urls":[{"url":"https:\/\/t.co\/7dGFqETrL0","expanded_url":"http:\/\/www.chelseafc.com","display_url":"chelseafc.com","indices":[0,23]}]},"description":{"urls":[{"url":"https:\/\/t.co\/6AE0WNqdOH","expanded_url":"http:\/\/che.lc\/iBt6ES","display_url":"che.lc\/iBt6ES","indices":[90,113]}]}},"protected":false,"followers_count":6745468,"friends_count":229,"listed_count":19627,"created_at":"Thu Mar 05 11:54:25 +0000 2009","favourites_count":10017,"utc_offset":3600,"time_zone":"London","geo_enabled":true,"verified":true,"statuses_count":57848,"lang":"en","contributors_enabled":false,"is_translator":false,"is_translation_enabled":true,"profile_background_color":"023F84","profile_background_image_url":"http:\/\/pbs.twimg.com\/profile_background_images\/636517723892252672\/DUnOnH-G.jpg","profile_background_image_url_https":"https:\/\/pbs.twimg.com\/profile_background_images\/636517723892252672\/DUnOnH-G.jpg","profile_background_tile":false,"profile_image_url":"http:\/\/pbs.twimg.com\/profile_images\/668322198537531392\/9BcEHF15_normal.jpg","profile_image_url_https":"https:\/\/pbs.twimg.com\/profile_images\/668322198537531392\/9BcEHF15_normal.jpg","profile_banner_url":"https:\/\/pbs.twimg.com\/profile_banners\/22910295\/1457103014","profile_link_color":"375EF1","profile_sidebar_border_color":"FFFFFF","profile_sidebar_fill_color":"37D3FA","profile_text_color":"000000","profile_use_background_image":true,"has_extended_profile":false,"default_profile":false,"default_profile_image":false,"following":false,"follow_request_sent":false,"notifications":false},"geo":null,"coordinates":null,"place":null,"contributors":null,"is_quote_status":false,"retweet_count":827,"favorite_count":576,"favorited":false,"retweeted":false,"lang":"en"},"is_quote_status":false,"retweet_count":827,"favorite_count":0,"favorited":false,"retweeted":false,"lang":"en"},{"created_at":"Sat Apr 02 12:13:46 +0000 2016","id":716237186446843904,"id_str":"716237186446843904","text":"RT @premierleague: GOAL Aston Villa 0-1 Chelsea (26 mins). Azpilicueta finds Loftus-Cheek in the box and his shot is deflected in off Lesco\u2026","entities":{"hashtags":[{"text":"AVLCHE","indices":[139,140]}],"symbols":[],"user_mentions":[{"screen_name":"premierleague","name":"Premier League","id":343627165,"id_str":"343627165","indices":[3,17]}],"urls":[]},"truncated":false,"metadata":{"iso_language_code":"en","result_type":"recent"},"source":"\u003ca href=\"http:\/\/twitter.com\" rel=\"nofollow\"\u003eTwitter Web Client\u003c\/a\u003e","in_reply_to_status_id":null,"in_reply_to_status_id_str":null,"in_reply_to_user_id":null,"in_reply_to_user_id_str":null,"in_reply_to_screen_name":null,"user":{"id":140490575,"id_str":"140490575","name":"emilio lopez sanchez","screen_name":"emiliolosa","location":"","description":"REAL MADRID SIEMPRE,Sporting, Benfica,Juve,OL,OM,Ajax,Anderlecht, Molde,Basel,BVB,Hertha,Hoff,Chelsea, Saints,Bournemouth,Everton,Newcastle,Kobenhavn","url":null,"entities":{"description":{"urls":[]}},"protected":false,"followers_count":199,"friends_count":431,"listed_count":2,"created_at":"Wed May 05 16:39:00 +0000 2010","favourites_count":1758,"utc_offset":7200,"time_zone":"Madrid","geo_enabled":true,"verified":false,"statuses_count":30869,"lang":"es","contributors_enabled":false,"is_translator":false,"is_translation_enabled":false,"profile_background_color":"1D5D7D","profile_background_image_url":"http:\/\/pbs.twimg.com\/profile_background_images\/484305006384787456\/lZRlMnLB.jpeg","profile_background_image_url_https":"https:\/\/pbs.twimg.com\/profile_background_images\/484305006384787456\/lZRlMnLB.jpeg","profile_background_tile":true,"profile_image_url":"http:\/\/pbs.twimg.com\/profile_images\/695260970436972544\/m6-3ZbNy_normal.jpg","profile_image_url_https":"https:\/\/pbs.twimg.com\/profile_images\/695260970436972544\/m6-3ZbNy_normal.jpg","profile_banner_url":"https:\/\/pbs.twimg.com\/profile_banners\/140490575\/1450482359","profile_link_color":"FF0015","profile_sidebar_border_color":"FFFFFF","profile_sidebar_fill_color":"EFEFEF","profile_text_color":"333333","profile_use_background_image":true,"has_extended_profile":true,"default_profile":false,"default_profile_image":false,"following":false,"follow_request_sent":false,"notifications":false},"geo":null,"coordinates":null,"place":null,"contributors":null,"retweeted_status":{"created_at":"Sat Apr 02 12:11:36 +0000 2016","id":716236640197468160,"id_str":"716236640197468160","text":"GOAL Aston Villa 0-1 Chelsea (26 mins). Azpilicueta finds Loftus-Cheek in the box and his shot is deflected in off Lescott #AVLCHE","entities":{"hashtags":[{"text":"AVLCHE","indices":[123,130]}],"symbols":[],"user_mentions":[],"urls":[]},"truncated":false,"metadata":{"iso_language_code":"en","result_type":"recent"},"source":"\u003ca href=\"http:\/\/twitter.com\" rel=\"nofollow\"\u003eTwitter Web Client\u003c\/a\u003e","in_reply_to_status_id":null,"in_reply_to_status_id_str":null,"in_reply_to_user_id":null,"in_reply_to_user_id_str":null,"in_reply_to_screen_name":null,"user":{"id":343627165,"id_str":"343627165","name":"Premier League","screen_name":"premierleague","location":"","description":"Official Twitter account of the Premier League #BPL http:\/\/t.co\/wF29U6HqBW","url":"http:\/\/t.co\/lbJkOEIneJ","entities":{"url":{"urls":[{"url":"http:\/\/t.co\/lbJkOEIneJ","expanded_url":"http:\/\/www.premierleague.com","display_url":"premierleague.com","indices":[0,22]}]},"description":{"urls":[{"url":"http:\/\/t.co\/wF29U6HqBW","expanded_url":"http:\/\/instagram.com\/premierleague","display_url":"instagram.com\/premierleague","indices":[52,74]}]}},"protected":false,"followers_count":11257345,"friends_count":23,"listed_count":18788,"created_at":"Wed Jul 27 21:09:32 +0000 2011","favourites_count":614,"utc_offset":3600,"time_zone":"London","geo_enabled":true,"verified":true,"statuses_count":63967,"lang":"en","contributors_enabled":false,"is_translator":false,"is_translation_enabled":true,"profile_background_color":"050528","profile_background_image_url":"http:\/\/pbs.twimg.com\/profile_background_images\/378800000161701914\/r0W2wiQt.jpeg","profile_background_image_url_https":"https:\/\/pbs.twimg.com\/profile_background_images\/378800000161701914\/r0W2wiQt.jpeg","profile_background_tile":false,"profile_image_url":"http:\/\/pbs.twimg.com\/profile_images\/1466012174\/PL-Twitter-Icon_normal.jpg","profile_image_url_https":"https:\/\/pbs.twimg.com\/profile_images\/1466012174\/PL-Twitter-Icon_normal.jpg","profile_banner_url":"https:\/\/pbs.twimg.com\/profile_banners\/343627165\/1458552904","profile_link_color":"93A644","profile_sidebar_border_color":"FFFFFF","profile_sidebar_fill_color":"171838","profile_text_color":"FFFFFF","profile_use_background_image":false,"has_extended_profile":false,"default_profile":false,"default_profile_image":false,"following":false,"follow_request_sent":false,"notifications":false},"geo":null,"coordinates":null,"place":null,"contributors":null,"is_quote_status":false,"retweet_count":406,"favorite_count":363,"favorited":false,"retweeted":false,"lang":"en"},"is_quote_status":false,"retweet_count":406,"favorite_count":0,"favorited":false,"retweeted":false,"lang":"en"}],"search_metadata":{"completed_in":0.074,"max_id":716237192750882820,"max_id_str":"716237192750882820","next_results":"?max_id=716237186446843903&q=%23CFCLive%20OR%20%23avlche%20since%3A2016-04-02%20until%3A2016-04-03&include_entities=1","query":"%23CFCLive+OR+%23avlche+since%3A2016-04-02+until%3A2016-04-03","refresh_url":"?since_id=716237192750882820&q=%23CFCLive%20OR%20%23avlche%20since%3A2016-04-02%20until%3A2016-04-03&include_entities=1","count":15,"since_id":0,"since_id_str":"0"}}